LICENSE.txt
MANIFEST.in
requirements.txt
setup.cfg
setup.py
versioneer.py
rqrisk/__init__.py
rqrisk/_version.py
rqrisk/risk.py
rqrisk/utils.py
rqrisk.egg-info/PKG-INFO
rqrisk.egg-info/SOURCES.txt
rqrisk.egg-info/dependency_links.txt
rqrisk.egg-info/not-zip-safe
rqrisk.egg-info/requires.txt
rqrisk.egg-info/top_level.txt